dgutwater/__init__.py
dgutwater/water.py
dgutwater-0.0.1.dist-info/LICENSE.txt
dgutwater-0.0.1.dist-info/METADATA
dgutwater-0.0.1.dist-info/WHEEL
dgutwater-0.0.1.dist-info/top_level.txt
dgutwater-0.0.1.dist-info/RECORD
